libscrappy.abi3.so
scrappy/__init__.py
scrappie-1.4.2.dist-info/DESCRIPTION.rst
scrappie-1.4.2.dist-info/WHEEL
scrappie-1.4.2.dist-info/RECORD
scrappie-1.4.2.dist-info/entry_points.txt
scrappie-1.4.2.dist-info/metadata.json
scrappie-1.4.2.dist-info/top_level.txt
scrappie-1.4.2.dist-info/METADATA
.libslibscrappy/libopenblasp-r0-39a31c03.2.18.so
.libslibscrappy/libgfortran-ed201abd.so.3.0.0
scrappie-1.4.2.data/data/OPENBLAS_LICENSE
