Metadata-Version: 2.0
Name: scrappie
Version: 1.4.2
Summary: Python bindings to scrappie basecaller
Home-page: https://github.com/nanoporetech/scrappie
Author: cwright
Author-email: cwright@nanoporetech.com
License: MPL 2.0
Platform: UNKNOWN
Classifier: Development Status :: 3 - Alpha
Classifier: Environment :: Console
Classifier: Intended Audience :: Developers
Classifier: Intended Audience :: Science/Research
Classifier: License :: OSI Approved :: Mozilla Public License 2.0 (MPL 2.0)
Classifier: Natural Language :: English
Classifier: Operating System :: Unix
Classifier: Programming Language :: Python :: 3 :: Only
Classifier: Topic :: Scientific/Engineering :: Artificial Intelligence
Classifier: Topic :: Scientific/Engineering :: Bio-Informatics
Classifier: Topic :: Scientific/Engineering :: Mathematics
Requires-Python: ~=3.4
Requires-Dist: cffi (>=1.0.0)
Requires-Dist: h5py
Requires-Dist: numpy
